cnr-0.4.1.data/scripts/cnr
cnr-0.4.1.dist-info/DESCRIPTION.rst
cnr-0.4.1.dist-info/METADATA
cnr-0.4.1.dist-info/RECORD
cnr-0.4.1.dist-info/WHEEL
cnr-0.4.1.dist-info/metadata.json
cnr-0.4.1.dist-info/top_level.txt
cnrclient/__init__.py
cnrclient/auth.py
cnrclient/client.py
cnrclient/config.py
cnrclient/discovery.py
cnrclient/display.py
cnrclient/pack.py
cnrclient/utils.py
cnrclient/commands/__init__.py
cnrclient/commands/channel.py
cnrclient/commands/cli.py
cnrclient/commands/command_base.py
cnrclient/commands/config.py
cnrclient/commands/delete_package.py
cnrclient/commands/helm.py
cnrclient/commands/inspect.py
cnrclient/commands/list_package.py
cnrclient/commands/login.py
cnrclient/commands/logout.py
cnrclient/commands/plugins.py
cnrclient/commands/pull.py
cnrclient/commands/push.py
cnrclient/commands/show.py
cnrclient/commands/version.py
cnrclient/commands/plugins/helm/cnr.sh
cnrclient/commands/plugins/helm/plugin.yaml
cnrclient/formats/__init__.py
cnrclient/formats/kub_base.py
cnrclient/formats/helm/__init__.py
cnrclient/formats/helm/chart.py
cnrclient/formats/helm/manifest_chart.py
cnrclient/formats/kpm/__init__.py
cnrclient/formats/kpm/kpm.py
cnrclient/plugins/__init__.py
cnrclient/plugins/helm.py
